Metadata-Version: 2.1
Name: password-generator-spg-melvinsatheesan
Version: 0.0.1
Summary: The package is intended to generate a secure and complex password
Home-page: UNKNOWN
Author: Melvin Satheesan
Author-email: melvinsatheesan@gmail.com
License: MIT
Keywords: password
Platform: UNKNOWN
Classifier: Development Status :: 5 - Production/Stable
Classifier: Intended Audience :: Education
Classifier: Operating System :: Microsoft :: Windows :: Windows 10
Classifier: License :: OSI Approved :: MIT License
Classifier: Programming Language :: Python :: 3
License-File: LICENCE.txt
